plover_search_translation/__init__.py
plover_search_translation/commands.py
plover_search_translation/dictionary.py
plover_search_translation/gui.py
plover_search_translation/lib.py
plover_search_translation/manager.py
plover_search_translation/process.py
plover_search_translation/py.typed
plover_search_translation/search_translation_dialog_ui.py
plover_search_translation/scripts/__init__.py
plover_search_translation/scripts/add_to_dict.py
plover_search_translation-0.7.0.dist-info/licenses/LICENSE
plover_search_translation-0.7.0.dist-info/METADATA
plover_search_translation-0.7.0.dist-info/WHEEL
plover_search_translation-0.7.0.dist-info/entry_points.txt
plover_search_translation-0.7.0.dist-info/top_level.txt
plover_search_translation-0.7.0.dist-info/zip-safe
plover_search_translation-0.7.0.dist-info/RECORD
