Metadata-Version: 2.4
Name: plover-search-translation
Version: 0.7.0
Summary: Dictionary plugin for Plover.
Author: user202729
License: GNU General Public License v3 or later (GPLv3+)
Keywords: plover plover_plugin
Classifier: Environment :: Plugins
Classifier: License :: OSI Approved :: GNU General Public License v3 or later (GPLv3+)
Classifier: Operating System :: OS Independent
Classifier: Programming Language :: Python :: 3
License-File: LICENSE
Requires-Dist: plover>=5.0.0
Requires-Dist: subprocess-connection>=0.0.5
Requires-Dist: fuzzywuzzy>=0.18.0
Provides-Extra: gui
Requires-Dist: PySide6-Essentials==6.9.0; extra == "gui"
Dynamic: license-file
